datasette_render_html.py
datasette_render_html-1.0.dist-info/METADATA
datasette_render_html-1.0.dist-info/WHEEL
datasette_render_html-1.0.dist-info/entry_points.txt
datasette_render_html-1.0.dist-info/top_level.txt
datasette_render_html-1.0.dist-info/RECORD
