Metadata-Version: 2.1
Name: datasette-render-html
Version: 1.0
Summary: Datasette plugin that renders specified cells as HTML
Home-page: https://github.com/simonw/datasette-render-html
Author: Simon Willison
License: Apache License, Version 2.0
Requires-Dist: datasette
Provides-Extra: test
Requires-Dist: pytest ; extra == 'test'
